so_pip/.gitignore
so_pip/__init__.py
so_pip/__main__.py
so_pip/_cache/.gitignore
so_pip/_cache/__init__.py
so_pip/_cache/pypi.html
so_pip/_vendor/__init__.py
so_pip/_vendor/find_imports/__init__.py
so_pip/_vendor/find_imports/main.py
so_pip/_vendor/find_imports_cruft/AUTHORS.txt
so_pip/_vendor/find_imports_cruft/CHANGELOG.txt
so_pip/_vendor/find_imports_cruft/CODE_OF_CONDUCT.txt
so_pip/_vendor/find_imports_cruft/LICENSE/CC BY-SA 2.5.txt
so_pip/_vendor/find_imports_cruft/LICENSE/CC BY-SA 3.0.txt
so_pip/_vendor/find_imports_cruft/LICENSE/CC BY-SA 4.0.txt
so_pip/_vendor/find_imports_cruft/README.md
so_pip/_vendor/find_imports_cruft/post.html
so_pip/_vendor/find_imports_cruft/post.md
so_pip/_vendor/find_imports_cruft/post.txt
so_pip/_vendor/find_imports_cruft/setup.cfg
so_pip/_vendor/find_imports_cruft/setup.py
so_pip/_version.py
so_pip/api_clients/__init__.py
so_pip/api_clients/pypstats_facade.py
so_pip/api_clients/pystackexchange_facade.py
so_pip/api_clients/search_engine_facade.py
so_pip/api_clients/stackapi_facade.py
so_pip/api_clients/stackoverflow_scraper.py
so_pip/api_clients/what_that_code_facade.py
so_pip/cli_clients/__init__.py
so_pip/cli_clients/external_commands.py
so_pip/cli_clients/pylintrc.ini
so_pip/cli_clients/subprocess_utils.py
so_pip/commands/__init__.py
so_pip/commands/freeze.py
so_pip/commands/list_all.py
so_pip/commands/search.py
so_pip/commands/show.py
so_pip/commands/uninstall.py
so_pip/commands/vendorize.py
so_pip/file_writing.py
so_pip/infer_packages_needed/.gitignore
so_pip/infer_packages_needed/README.md
so_pip/infer_packages_needed/__init__.py
so_pip/infer_packages_needed/package_by_name.py
so_pip/infer_packages_needed/parse_imports.py
so_pip/licenses/CC BY-SA 2.0.html
so_pip/licenses/CC BY-SA 2.0.txt
so_pip/licenses/CC BY-SA 2.5.html
so_pip/licenses/CC BY-SA 2.5.txt
so_pip/licenses/CC BY-SA 3.0.txt
so_pip/licenses/CC BY-SA 4.0.txt
so_pip/licenses/convert_to_txt.py
so_pip/make_from_template.py
so_pip/models/__init__.py
so_pip-0.3.0.dist-info/LICENSE
so_pip-0.3.0.dist-info/METADATA
so_pip-0.3.0.dist-info/WHEEL
so_pip-0.3.0.dist-info/entry_points.txt
so_pip-0.3.0.dist-info/RECORD
