Metadata-Version: 2.1
Name: so-pip
Version: 0.3.0
Summary: Generate packages from Stackoverflow answers
Home-page: https://github.com/matthewdeanmartin/so_pip
License: MIT
Keywords: packaging,stackoverflow
Author: Matthew Martin
Author-email: matthewdeanmartin@gmail.com
Requires-Python: >=3.11
Classifier: Development Status :: 3 - Alpha
Classifier: Intended Audience :: Developers
Classifier: License :: OSI Approved :: MIT License
Classifier: Operating System :: OS Independent
Classifier: Programming Language :: Python
Classifier: Programming Language :: Python :: 3
Classifier: Programming Language :: Python :: 3.11
Classifier: Programming Language :: Python :: 3.7
Classifier: Programming Language :: Python :: 3.8
Classifier: Programming Language :: Python :: 3.9
Requires-Dist: 2to3
Requires-Dist: astroid
Requires-Dist: beautifulsoup4
Requires-Dist: black
Requires-Dist: diskcache
Requires-Dist: html2text
Requires-Dist: jinja2
Requires-Dist: markdown
Requires-Dist: nbformat
Requires-Dist: pip-upgrader
Requires-Dist: pipreqs
Requires-Dist: pur
Requires-Dist: py-stackexchange
Requires-Dist: pyflakes
Requires-Dist: pypinfo
Requires-Dist: pypistats
Requires-Dist: pyrankvote
Requires-Dist: python-dotenv
Requires-Dist: pyupgrade
Requires-Dist: random-names
Requires-Dist: requests
Requires-Dist: safety
Requires-Dist: search-engine-parser
Requires-Dist: slpp-23
Requires-Dist: stackapi
Requires-Dist: stdlib-list
Requires-Dist: toml
Requires-Dist: vermin
Requires-Dist: whats-that-code (>=0.1.10)
Project-URL: Bug Tracker, https://github.com/matthewdeanmartin/so_pip/issues
Project-URL: Change Log, https://github.com/matthewdeanmartin/so_pip/blob/main/CHANGES.md
Project-URL: Documentation, https://github.com/matthewdeanmartin/so_pip
Project-URL: Repository, https://github.com/matthewdeanmartin/so_pip
